[
  {
    "name": "The Southampton Model Railway Exhibition",
    "organizer": "Southampton Model Railway Society",
    "startDate": "2023-01-28",
    "endDate": "2023-01-29",
    "venue": "Barton Peveril College",
    "address": "Chestnut Avenue, Eastleigh",
    "county": "Hampshire",
    "layouts": 22,
    "traders": 22,
    "features": [
      "Club Stand",
      "Modelling Demonstrations"
    ],
    "amenities": [
      "Wheelchair Accessible",
      "Free Parking",
      "Refreshments"
    ],
    "transport": "Free heritage bus service between college and Eastleigh/Southampton Airport Parkway stations approximately every half hour from 9:30am",
    "description": "Barton Peveril College is about 1 1/2 miles from M3 Junc 13 or M27 Junc 5 and will be AA signed from shortly after the junctions. Eastleigh and Southampton Airport Parkway stations are both about 25 mins walk."
  },
  {
    "name": "Irvine Model Railway Exhibition",
    "organizer": "Kilmarnock & District Model Railway Club",
    "startDate": "2023-01-28",
    "endDate": "2023-01-29",
    "venue": "The Linthouse Building, Scottish Maritime Museum",
    "address": "Irvine, Ayrshire",
    "amenities": [
      "Wheelchair Accessible",
      "Free Parking",
      "Refreshments"
    ],
    "description": "After a very successful Exhibition in the Scottish Maritime Museum in 2022 it has been agreed that there will be an Exhibition in 2023."
  },
  {
    "name": "Model Railway Exhibition",
    "organizer": "Kendal Model Railway Club",
    "startDate": "2023-01-28",
    "endDate": "2023-01-29",
    "venue": "Leisure Centre",
    "address": "Burton Road, Kendal, Cumbria",
    "layouts": 12,
    "traders": 14,
    "features": [
      "Club Stand",
      "Modelling Demonstrations"
    ],
    "amenities": [
      "Wheelchair Accessible",
      "Free Parking",
      "Refreshments"
    ],
    "description": "Annual exhibition celebrating 60 years since the founding of Kendal Model Railway Club"
  },
  {
    "name": "Longfield Model Railway Exhibition 2023",
    "organizer": "Erith Model Railway Society",
    "startDate": "2023-01-28",
    "endDate": "2023-01-29",
    "venue": "The Longfield Academy",
    "address": "Main Road (B260), Longfield, Kent",
    "layouts": "30+",
    "traders": "40+",
    "features": [
      "Club Stand",
      "Modelling Demonstrations"
    ],
    "amenities": [
      "Wheelchair Accessible",
      "Free Parking",
      "Refreshments"
    ],
    "description": "The Erith Model Railway Society's January Exhibition, one of South East England's largest shows (And probably Kent's largest by stand numbers), will return to the Longfield Academy for our 6th show there (And our first since 2020). The show will continue to encompass at least 30 layouts, extensive trade and society support, demonstrators, static exhibits and charity raffle, making nearly 90 stands in total."
  },
  {
    "name": "Astolat Model Railway Club Exhibition",
    "organizer": "Astolat Model Railway Club",
    "startDate": "2026-07-12",
    "endDate": "2026-07-12",
    "venue": "Guildford Spectrum",
    "address": "Parkway, Guildford, GU1 1UP",
    "county": "Surrey",
    "layouts": 0,
    "traders": 0,
    "features": [],
    "amenities": [],
    "admission": "",
    "description": "TBC",
    "latLng": "51.24903, -0.56293",
    "url": "https://astolatmrc.co.uk/"
  },
  {
    "name": "Exhibition",
    "organizer": "Basingstoke & North Hants Model Railway Society",
    "startDate": "2026-03-14",
    "endDate": "2026-03-15",
    "venue": "Blue Coat School",
    "address": "Western Way, Basingstoke, RG22 6HQ",
    "county": "Berkshire",
    "layouts": 0,
    "traders": 0,
    "features": [],
    "amenities": [],
    "specialFeatures": [],
    "description": "Step aboard for a journey through miniature worlds! Basingstoke & North Hants Model Railway Society is thrilled to host another highly anticipated Model Railway Show in 2026, Where the magic of railways comes to life in stunning detail! Please join us to see a great line-up of Layouts, Societies, and Traders!",
    "latLng": "51.25442, -1.11723",
    "url": "https://basingstokemrs.uk/basingstoke-model-railway-show-2026/"
  },
  {
    "name": "Exhibition",
    "organizer": "Roxley Models",
    "startDate": "2026-05-16",
    "endDate": "2026-05-17",
    "venue": "Denbies Wine Estate",
    "address": "Bradley Lane, Dorking, RH5 6AA",
    "county": "Surrey",
    "layouts": "TBC",
    "traders": "TBC",
    "features": [],
    "amenities": [],
    "specialFeatures": [],
    "description": "Join us for a special Model Railway Exhibition at Denbies Wine Estate, celebrating the 40th Anniversary of Roxley Models, set against the stunning backdrop of the Surrey Hills. This family-friendly event is perfect for enthusiasts, hobbyists, and anyone curious about the world of model railways. ",
    "latLng": "51.24815, -0.33186",
    "url": "https://www.roxleymodels.co.uk/article_info.php?articles_id=24"
  },
  {
    "name": "Febex 2026",
    "organizer": "Alton Model Railway Group",
    "startDate": "2026-02-07",
    "endDate": "2026-02-08",
    "venue": "Eggars School",
    "address": "Alton, GU34 4EQ",
    "county": "Hampshire",
    "layouts": "18+",
    "traders": 17,
    "features": [],
    "amenities": [],
    "specialFeatures": [],
    "description": "",
    "latLng": "51.15985, -0.95914",
    "url": "https://febex.co.uk/"
  },
  {
    "name": "Club Exhibition",
    "organizer": "East Bedfordshire Model railway Society",
    "startDate": "2026-02-14",
    "endDate": "2026-02-14",
    "venue": "Statton School",
    "address": "Eagle Farm Road, SG18 8JB",
    "county": "Bedfordshire",
    "layouts": "15+",
    "traders": "",
    "features": [],
    "amenities": [],
    "specialFeatures": [],
    "description": "",
    "latLng": "52.08664, -0.25019",
    "url": "https://ebmrs.org/club-exhibition/"
  },
  {
    "name": "RISEX",
    "organizer": "Risborough and District Model Railway Club",
    "startDate": "2026-02-21",
    "endDate": "2026-02-21",
    "venue": "Wades Centre",
    "address": "Wades Park, Stratton Rd, Risborough, HP27 9AX",
    "county": "Buckinghamshire",
    "layouts": "8",
    "traders": "2",
    "features": [],
    "amenities": [],
    "specialFeatures": [],
    "description": "",
    "latLng": "51.72376, -0.83782",
    "url": "https://www.rdmrc.org.uk/doku.php?id=exhibitions:risex:risex26"
  },
  {
    "name": "RAILEX",
    "organizer": "Risborough and District Model Railway Club",
    "startDate": "2026-05-23",
    "endDate": "2026-05-24",
    "venue": "Stoke Mandeville Stadium",
    "address": "Harvey Road, Aylesbury, HP21 9PP",
    "county": "Buckinghamshire",
    "layouts": "22",
    "traders": "30+",
    "features": [],
    "amenities": [],
    "specialFeatures": [],
    "description": "",
    "latLng": "51.72376, -0.83782",
    "url": "https://www.railex.org.uk/doku.php"
  },
  {
    "name": "Exhibition",
    "organizer": "Tonbridge Model Railway Club",
    "startDate": "2026-02-21",
    "endDate": "2026-02-21",
    "venue": "Angel Centre",
    "address": "Tonbridge, TN9 1SF",
    "county": "Kent",
    "layouts": "23",
    "traders": "24",
    "features": [],
    "amenities": [],
    "specialFeatures": [],
    "description": "",
    "latLng": "51.19245, 0.27495",
    "url": "https://www.tonbridgemrc.com/exhibition"
  },
  {
    "name": "Exhibition 2026",
    "organizer": "Hampton Court Model Railway Society",
    "startDate": "2026-11-07",
    "endDate": "2026-11-08",
    "venue": " Tolworth Recreation Centre",
    "address": "Fullers Way North, Tolworth, Surrey, KT6 7LQ",
    "county": "Surrey",
    "layouts": "32",
    "traders": "7+",
    "features": [
      "Model railway layouts",
      "Trade stands",
      "Refreshments available"
    ],
    "amenities": [
      "Free parking",
      "Disabled access",
      "Cafe"
    ],
    "specialFeatures": [
      "Various scales including N, OO, O gauge",
      "Local and visiting layouts"
    ],
    "description": "Annual model railway exhibition organized by Hampton Court Model Railway Society featuring multiple layouts across different scales, trade stands, and refreshments. ",
    "latLng": "51.37552, -0.29629",
    "url": "https://www.hamptoncourtmrs.co.uk/showtrain/showtrain%202026.html"
  },
  {
    "name": "The London Festival of Railway Modelling",
    "organizer": "Warners Group Publications",
    "startDate": "2024-03-21",
    "endDate": "2024-03-22",
    "venue": "Alexandra Palace",
    "address": "Alexandra Palace Way, London, N22 7AY",
    "county": "Greater London",
    "layouts": "50+",
    "traders": "80+",
    "features": [
      "Model railway layouts",
      "Trade stands",
      "Demonstrations",
      "Special guests",
      "Bring and buy stall"
    ],
    "amenities": [
      "Parking available",
      "Refreshments available",
      "Disabled access"
    ],
    "specialFeatures": [
      "Largest model railway show in London",
      "Wide variety of scales and gauges",
      "Expert talks and demonstrations"
    ],
    "description": "The London Festival of Railway Modelling is one of the UK's premier model railway exhibitions, featuring over 50 layouts covering all scales and gauges, more than 80 traders, demonstrations, and special guests. Held at the iconic Alexandra Palace, this two-day event showcases the best of railway modelling.",
    "latLng": "51.59448, -0.13053",
    "url": "https://www.world-of-railways.co.uk/information/the-london-festival-of-railway-modelling"
  },
  {
    "name": "The Festival of British Railway Modelling - Exhibition",
    "organizer": "Warners Group Publications",
    "startDate": "2025-02-07",
    "endDate": "2025-02-08",
    "venue": "Peterborough Arena",
    "address": "Peterborough Arena, Mallard Road, Peterborough, PE4 6NA",
    "county": "Cambridgeshire",
    "layouts": "40",
    "traders": "100",
    "features": [
      "Model railway layouts",
      "Trade stands",
      "Demonstrations",
      "Clinics and workshops"
    ],
    "amenities": [
      "Free parking",
      "Refreshments available",
      "Wheelchair accessible"
    ],
    "specialFeatures": [
      "UK's largest model railway exhibition",
      "All scales and gauges represented",
      "Live steam area",
      "Kids activities"
    ],
    "description": "The Festival of British Railway Modelling is the UK's largest model railway exhibition featuring layouts in all scales and gauges, over 100 trade stands, demonstrations, workshops and activities for all the family.",
    "latLng": "52.5693, -0.2358",
    "url": "https://www.world-of-railways.co.uk/information/the-festival-of-british-railway-modelling"
  },
  {
    "name": "The International N Gauge Show - Exhibition",
    "organizer": "Meridiènne Exhibitions",
    "startDate": "2026-09-12",
    "endDate": "2026-09-13",
    "venue": "Warwickshire Event Centre",
    "address": "TWarwickshire Event Centre, A425, Southam Road, Leamington Spa, CV31 1FE",
    "county": "Warwickshire",
    "layouts": "TBC",
    "traders": "TBC",
    "features": [
      "N Gauge layouts",
      "Trade stands",
      "Demonstrations",
      "Competitions"
    ],
    "amenities": [
      "Free parking",
      "Café",
      "Disabled access",
      "Toilets"
    ],
    "specialFeatures": [
      "International N Gauge exhibition",
      "One of the largest N Gauge shows in the UK",
      "Weekend event"
    ],
    "description": "The International N Gauge Show is one of the premier N Gauge exhibitions in the UK, featuring around 60 layouts from across the country and internationally, alongside approximately 40 trade stands. The show includes demonstrations, competitions, and provides a comprehensive showcase of N Gauge railway modelling.",
    "latLng": "52.27047, -1.46880",
    "url": "https://www.meridienneexhibitions.co.uk/events/the-international-n-gauge-show"
  },
  {
    "name": "BMRE 2026",
    "organizer": "East Dorset N Gauge Group",
    "startDate": "2026-02-14",
    "endDate": "2026-02-15",
    "venue": "Kinson Community Centre",
    "address": "Pelhams Park, Millhams Road, Kinson, BH10 7LH",
    "county": "Dorset",
    "layouts": "27",
    "traders": "9",
    "features": [],
    "amenities": [],
    "specialFeatures": [],
    "description": "All aboard the Bournemouth model railway exhibition 2026. After a very successful exhibition in 2025 that saw 1,111 visitors attend the show at the Hamworthy club. Join us at our new venue, Kinson community centre. With over 24 layouts and full trade and society's attending.",
    "latLng": "50.77139, -1.90056",
    "url": "https://bmre.org.uk/"
  },
  {
    "name": "Railex 2026",
    "organizer": "Portsmouth Model Railway Club",
    "startDate": "2026-02-21",
    "endDate": "2026-02-22",
    "venue": "Horndean Technology College",
    "address": "Horndean, Barton Cross, Horndean PO8 9PQ",
    "county": "Hampshire",
    "layouts": "20+",
    "traders": "10",
    "features": [
      "Model railway layouts",
      "Trade stands",
      "Demonstration areas",
      "Multiple gauges"
    ],
    "amenities": [
      "Free parking",
      "Refreshments available",
      "Disabled access",
      "Toilets"
    ],
    "specialFeatures": [
      "Large exhibition hall",
      "30 layouts from around the UK",
      "Wide range of scales and gauges",
      "Major traders present"
    ],
    "description": "Portsmouth Railex returns to Horndean Technology College on 21st & 22nd February 2026 showcasing 20+ layouts of various gauges from around the UK. Supported by traders and societies. A must visit exhibition for model railway enthusiasts and families of all ages.",
    "latLng": "50.91341, -1.01007",
    "url": "https://portsmouthrailex.wixsite.com/website"
  },
  {
    "name": "Exhibition",
    "organizer": "Lincoln and District Model Railway Club",
    "startDate": "2026-02-21",
    "endDate": "2026-02-22",
    "venue": "County Assembly Rooms",
    "address": "The Bailgate, Lincoln, LN1 3AR",
    "county": "Lincolnshire",
    "layouts": "19",
    "traders": "9",
    "features": [],
    "amenities": [],
    "specialFeatures": [],
    "description": "",
    "latLng": "53.23579, -0.53829",
    "url": ""
  },
  {
    "name": "Weston-Super-Mare Show 2026",
    "organizer": "Burnham and District Model Railway Club",
    "startDate": "2026-02-14",
    "endDate": "2026-02-15",
    "venue": "Priory Community School",
    "address": "Queens Way, Weston-super-Mare BS22 6BP",
    "county": "Somerset",
    "layouts": "25",
    "traders": "12",
    "features": [],
    "amenities": [],
    "specialFeatures": [],
    "description": "Annual model railway exhibition hosted by Burnham District Model Railway Club at Priory Community School, featuring around 20 layouts and 15 trade stands over two days.",
    "latLng": "51.36385, -2.90993",
    "url": "https://bdmrc.co.uk/weston-super-mare-2026/"
  },
  {
    "name": "ModRail 2026 Exhibition",
    "organizer": "Swindon Model Railway Club",
    "startDate": "2026-03-07",
    "endDate": "2026-03-07",
    "venue": "Museum of the Great Western Railway",
    "address": "Fire Fly Avenue, Swindon, SN2 2EY",
    "county": "Wiltshire",
    "layouts": "29",
    "traders": "9",
    "features": [
      "Model railway layouts",
      "Trade stands",
      "Refreshments available",
      "Free parking"
    ],
    "amenities": [
      "Wheelchair accessible",
      "Toilets",
      "Cafe/refreshments"
    ],
    "specialFeatures": [
      "Held at historic railway museum",
      "Large exhibition space",
      "Two-day event"
    ],
    "description": "ModRail 2026 is Swindon Model Railway Club's annual exhibition featuring around 20 model railway layouts and approximately 30 trade stands. The event takes place over two days at the STEAM Museum in Swindon.",
    "latLng": "51.56336, -1.79543",
    "url": "https://www.swindonmodelrailwayclub.com/index.php/modrail-2026"
  }
]